lsyzwmworkcore/__init__.py
lsyzwmworkcore/listener_base.py
lsyzwmworkcore/listener_manager.py
lsyzwmworkcore/node_change_tracker.py
lsyzwmworkcore/worker_base.py
lsyzwmworkcore/worker_manager.py
lsyzwmworkcore-0.0.4.dist-info/licenses/LICENSE
lsyzwmworkcore-0.0.4.dist-info/METADATA
lsyzwmworkcore-0.0.4.dist-info/WHEEL
lsyzwmworkcore-0.0.4.dist-info/top_level.txt
lsyzwmworkcore-0.0.4.dist-info/RECORD
