Metadata-Version: 2.4
Name: lsyzwmworkcore
Version: 0.0.4
Summary: lsyzwm-work-core - 简化work任务分发与执行的核心库
Author: 9kl
License-Expression: MIT
Keywords: lsyzwm-work-core
Classifier: Development Status :: 3 - Alpha
Classifier: Intended Audience :: Developers
Classifier: Programming Language :: Python :: 3
Classifier: Programming Language :: Python :: 3.8
Classifier: Programming Language :: Python :: 3.9
Classifier: Programming Language :: Python :: 3.10
Classifier: Programming Language :: Python :: 3.11
Classifier: Programming Language :: Python :: 3.12
Requires-Python: >=3.8
License-File: LICENSE
Requires-Dist: Twisted==24.11.0
Requires-Dist: lsyzwm-master-sdk==0.0.9
Provides-Extra: dev
Provides-Extra: test
Dynamic: license-file
